modusched/__init__.py
modusched/client.py
modusched/core.py
modusched/utils.py
modusched/protocols/__init__.py
modusched/protocols/protocols.py
modusched-1.0.4.dist-info/METADATA
modusched-1.0.4.dist-info/WHEEL
modusched-1.0.4.dist-info/top_level.txt
modusched-1.0.4.dist-info/RECORD
