Metadata-Version: 2.4
Name: modusched
Version: 1.0.4
Summary: Add your description here
Requires-Python: >=3.12
Requires-Dist: anyio>=4.11.0
Requires-Dist: deepagents>=0.2.5
Requires-Dist: dotenv>=0.9.9
Requires-Dist: fastapi>=0.119.1
Requires-Dist: httpx[http2]>=0.28.1
Requires-Dist: langchain-mcp-adapters>=0.1.12
Requires-Dist: langchain-openai>=1.0.2
Requires-Dist: sse-starlette>=2.3.3
Requires-Dist: toml>=0.10.2
Requires-Dist: uvicorn>=0.38.0
Requires-Dist: volcengine-python-sdk>=4.0.6
Requires-Dist: websockets>=15.0.1
